gan_recover_image/SRGan.py
gan_recover_image/__init__.py
gan_recover_image/test.py
gan_recover_image/Model/ImageModel.py
gan_recover_image/Model/__init__.py
gan_recover_image/NetWork/__init__.py
gan_recover_image/NetWork/factory_network.py
gan_recover_image/SRGAN/__init__.py
gan_recover_image/SRGAN/networks.py
gan_recover_image/SRGAN/training_ckp_generator/__init__.py
gan_recover_image/SRGAN/training_ckp_generator/checkpoint
gan_recover_image/SRGAN/training_ckp_generator/ckpt-42.data-00000-of-00001
gan_recover_image/SRGAN/training_ckp_generator/ckpt-42.index
gan_recover_image/SRGAN/training_ckp_generator/ckpt-43.data-00000-of-00001
gan_recover_image/SRGAN/training_ckp_generator/ckpt-43.index
gan_recover_image/result/__init__.py
gan_recover_image/result/SRGAN/__init__.py
gan_recover_image/result/SRGAN/b.jpg
gan_recover_image/result/SRGAN/result.jpg
gan_recover_image-0.1.6.dist-info/LICENSE
gan_recover_image-0.1.6.dist-info/METADATA
gan_recover_image-0.1.6.dist-info/WHEEL
gan_recover_image-0.1.6.dist-info/top_level.txt
gan_recover_image-0.1.6.dist-info/RECORD
