Metadata-Version: 2.1
Name: gan-recover-image
Version: 0.1.6
Summary: A package use to recovery image
Home-page: UNKNOWN
Author: Fujinet System SJC
Author-email: tumeotl@gmail.com
License: UNKNOWN
Platform: UNKNOWN
Classifier: Programming Language :: Python :: 3
Classifier: License :: OSI Approved :: MIT License
Classifier: Operating System :: OS Independent
Requires-Python: >=3.6
Requires-Dist: tensorflow (==2.4.0)
Requires-Dist: Pillow (==8.0.1)
Requires-Dist: numpy (==1.19.4)
